odoo8_addon_shopinvader_search_engine-8.0.0.0.1.99.dev10-py3.8-nspkg.pth
odoo_addons/shopinvader_search_engine/README.rst
odoo_addons/shopinvader_search_engine/__init__.py
odoo_addons/shopinvader_search_engine/__openerp__.py
odoo_addons/shopinvader_search_engine/data/ir_export_product.xml
odoo_addons/shopinvader_search_engine/models/__init__.py
odoo_addons/shopinvader_search_engine/models/backend.py
odoo_addons/shopinvader_search_engine/models/product.py
odoo_addons/shopinvader_search_engine/models/product_category.py
odoo_addons/shopinvader_search_engine/tests/__init__.py
odoo_addons/shopinvader_search_engine/tests/test_product.py
odoo_addons/shopinvader_search_engine/views/backend_view.xml
odoo_addons/shopinvader_search_engine/views/product_category_view.xml
odoo_addons/shopinvader_search_engine/views/product_view.xml
odoo8_addon_shopinvader_search_engine-8.0.0.0.1.99.dev10.dist-info/METADATA
odoo8_addon_shopinvader_search_engine-8.0.0.0.1.99.dev10.dist-info/WHEEL
odoo8_addon_shopinvader_search_engine-8.0.0.0.1.99.dev10.dist-info/namespace_packages.txt
odoo8_addon_shopinvader_search_engine-8.0.0.0.1.99.dev10.dist-info/top_level.txt
odoo8_addon_shopinvader_search_engine-8.0.0.0.1.99.dev10.dist-info/RECORD
